expr_parser/__init__.py
expr_parser/__main__.py
expr_parser/error.py
expr_parser/parser.py
expr_parser/tree.py
expr_parser/operators/__init__.py
expr_parser/operators/base.py
expr_parser/operators/default.py
expr_parser/operators/dice.py
gammelmath-0.0.1.dist-info/LICENSE
gammelmath-0.0.1.dist-info/METADATA
gammelmath-0.0.1.dist-info/WHEEL
gammelmath-0.0.1.dist-info/top_level.txt
gammelmath-0.0.1.dist-info/RECORD
