Metadata-Version: 2.1
Name: gammelmath
Version: 0.0.1
Summary: A fun project for parsing arithmetic expressions
Home-page: https://github.com/gammelalf/gammelmath
Author: Wolfgang Fischer
Author-email: 31348226+gammelalf@users.noreply.github.com
License: UNKNOWN
Platform: UNKNOWN
Classifier: Programming Language :: Python :: 3
Classifier: License :: OSI Approved :: GNU General Public License v2 or later (GPLv2+)
Classifier: Operating System :: OS Independent
Requires-Python: >=3.6
